automated_actions_client/__init__.py
automated_actions_client/client.py
automated_actions_client/errors.py
automated_actions_client/py.typed
automated_actions_client/types.py
automated_actions_client/api/__init__.py
automated_actions_client/api/actions/__init__.py
automated_actions_client/api/actions/external_resource_flush_elasticache.py
automated_actions_client/api/actions/external_resource_rds_reboot.py
automated_actions_client/api/actions/external_resource_rds_snapshot.py
automated_actions_client/api/actions/no_op.py
automated_actions_client/api/actions/openshift_trigger_cronjob.py
automated_actions_client/api/actions/openshift_workload_delete.py
automated_actions_client/api/actions/openshift_workload_restart.py
automated_actions_client/api/admin/__init__.py
automated_actions_client/api/admin/create_token.py
automated_actions_client/api/general/__init__.py
automated_actions_client/api/general/action_cancel.py
automated_actions_client/api/general/action_detail.py
automated_actions_client/api/general/action_list.py
automated_actions_client/api/general/me.py
automated_actions_client/models/__init__.py
automated_actions_client/models/action_schema_out.py
automated_actions_client/models/action_schema_out_task_args_type_0.py
automated_actions_client/models/action_status.py
automated_actions_client/models/create_token_param.py
automated_actions_client/models/http_validation_error.py
automated_actions_client/models/openshift_workload_restart_kind.py
automated_actions_client/models/user_schema_out.py
automated_actions_client/models/validation_error.py
automated_actions_client-0.1.6.dist-info/METADATA
automated_actions_client-0.1.6.dist-info/WHEEL
automated_actions_client-0.1.6.dist-info/RECORD
