Metadata-Version: 2.4
Name: automated-actions-client
Version: 0.1.6
Summary: Automated Actions Client
Project-URL: homepage, https://github.com/app-sre/automated-actions
Project-URL: repository, https://github.com/app-sre/automated-actions
Project-URL: documentation, https://github.com/app-sre/automated-actions
Author-email: AppSRE <sd-app-sre@redhat.com>
License: Apache 2.0
Requires-Python: ~=3.12.0
Requires-Dist: attrs
Requires-Dist: httpx
Requires-Dist: python-dateutil
Requires-Dist: typer
